[{"time":"2023-11-12 14:45:22","titulo":"Ministério Público pede prisão preventiva para Escária e Lacerda Machado","thumb":"https://images.impresa.pt/expresso/2023-11-09-3C2A7880-copy_T-_IDP.jpg-920e0407/1.91x1?wm=true&outputFormat=jpeg","desc":"Depois da declaração de António Costa ao país, na noite de sábado, o ministro do Ambiente, Duarte Cordeiro, sublinhou este domingo que não é arguido na Operação Influencer, e que continua a estar à disposição do primeiro-ministro. Siga aqui os desenvolvimentos da crise política","link":"https://expresso.pt/politica/crise/2023-11-10-PS-vai-a-votos-a-meio-de-dezembro.-Jose-Luis-Carneiro-candidato.-Costa-pede-ao-partido-que-evite-criticas-a-Justica-9439cba3"}]
