[{"time":"2023-09-05 18:20:19","titulo":"Conselho de Estado \"concluiu análise\" do país e reforçou apoio à Ucrânia","thumb":"https://media-manager.noticiasaominuto.com/1280/naom_64f76aa963252.jpg","desc":"Nota informativa dá conta da reafirmada \"solidariedade e admiração pela resistência do povo ucraniano\" relativamente à invasão russa iniciada em fevereiro de 2022... \"com plena concordância entre os órgãos políticos de soberania\".","link":"https://www.noticiasaominuto.com/pais/2393738/conselho-de-estado-concluiu-analise-do-pais-e-reforcou-apoio-a-ucrania"}]
