[{"time":"2023-11-19 20:45:12","titulo":"Ana Markovic: \"Não me chamem a jogadora mais sexy do mundo porque não me vejo assim\"","thumb":"https://thumbs.web.sapo.io/?W=1200&H=630&png=1&delay_optim=1&tv=1&crop=center&bottom_overlay=https%3A%2F%2Fsapo24.web.sapo.io%2Fassets%2Fimg%2F24-sapo%2Ffacebook-overlay.png&epic=ZDVl+0dTtu7Ws2JhvL2ik0Qk3rOlFiYzj43KKWNwvbwHwaUq3pxAMcCj7ornnNSuWfawyFRPvBGpnPXzNRWMoR8EY6nKgqoFRbBGLWAgfvQqICU=","desc":"Ana Markovic, internacional croata, esteve na Web Summit para falar de redes sociais e futebol feminino. Tem 2,9 milhões de seguidores no Instagram. Recusou um convite de Inglaterra ...","link":"https://24.sapo.pt/desporto/artigos/ana-markovic-nao-me-chamem-a-jogadora-mais-sexy-do-mundo-porque-nao-me-vejo-assim"}]
