[{"time":"2023-11-11 14:25:39","titulo":"AO MINUTO: António Costa fala ao país às 20h; Audição de Escária começou","thumb":"https://media-manager.noticiasaominuto.com/1280/naom_5b4ca59f46f8c.jpg","desc":"Acompanhe aqui AO MINUTO todos os desenvolvimentos da crise política em Portugal, após as buscas do Ministério Público a negócios de lítio e hidrogénio verde, que tiveram como consequência a demissão do primeiro-ministro.","link":"https://www.noticiasaominuto.com/pais/2438801/ao-minuto-antonio-costa-fala-ao-pais-as-20h-audicao-de-escaria-comecou"}]
