[{"time":"2023-12-19 20:45:30","titulo":"Proximidade com Salgado é “mentira e mistificação histórica”, diz Sócrates","thumb":"https://imagens.publico.pt/imagens.aspx/1868366?tp=UH&db=IMAGENS&type=JPG&share=1&o=BarraFacebook_Publico.png","desc":"O ex-governante testemunhou no julgamento de Pinho. Durão e Passos Coelho também foram a tribunal para firmar que banqueiro nunca usou a sua posição para obter vantagens.","link":"https://www.publico.pt/2023/12/19/sociedade/noticia/proximidade-salgado-mentira-mistificacao-historica-socrates-2074271"}]
