[{"time":"2023-11-13 22:46:09","titulo":"Pedro Nuno, candidato a líder do PS, admite “erros” e promete aprender com eles","thumb":"https://imagens.publico.pt/imagens.aspx/1858608?tp=UH&db=IMAGENS&type=JPG&share=1&o=BarraFacebook_Publico.png","desc":"Ex-ministro elogiou o legado de António Costa e defendeu que não se devem passar os próximos quatro meses a discutir o processo judicial. Salários, habitação e coesão são as suas preocupações centrais","link":"https://www.publico.pt/2023/11/13/politica/noticia/pedro-nuno-santos-candidato-lideranca-ps-2070045"}]
