[{"time":"2023-09-19 20:46:38","titulo":"\"Salário mínimo mantém isenção de IRS\", Costa desmente Ministério das Finanças","thumb":"https://images.impresa.pt/sicnot/2023-09-19-Governo-Antonio-Costa-eb228c44/1.91x1?wm=true&outputFormat=jpeg","desc":"Durante o debate da moção de censura ao Governo apresentado pelo Chega, o governante assegura que quem ganha o salário mínimo vai continuar a não pagar IRS.","link":"https://sicnoticias.pt/pais/2023-09-19-Salario-minimo-mantem-isencao-de-IRS-Costa-desmente-Ministerio-das-Financas-3e8a1a43"}]
