[{"time":"2023-12-16 21:46:20","titulo":"José Luís Carneiro afirma-se \"disponível para o PS\" - Renascença","thumb":"https://images.rr.sapo.pt/419262102184cb52ea44_socialshare.JPG","desc":"Jos&#233; Lu&#237;s Carneiro chegou pelas 20h30 ao hotel em que estavam os elementos da sua candidatura, acompanhado da fam&#237;lia, tendo sido ladeado por alguns apoiantes presentes, como o ex-ministro Jos&#233; Ant&#243;nio Vieira da Silva, o secret&#225;rio de Estado Andr&#233; Moz Caldas ou a deputada Jamila Madeira, e deixou uma &quot;palavra de gratid&#227;o&quot; aos que o acompanharam na campanha interna socialista.","link":"https://rr.sapo.pt/noticia/politica/2023/12/16/jose-luis-carneiro-afirma-se-disponivel-para-o-ps/359461/"}]
