[{"time":"2023-09-07 16:07:30","titulo":"Número de casos de covid-19 dispara, pico atingido no final de agosto","thumb":"https://images.impresa.pt/sicnot/2023-09-07-covid-19-covid-teste.jpg-24711214-1/1.91x1?wm=true&outputFormat=jpeg","desc":"O número de infeções por covid-19 está a aumentar e atingiu um pico no final de agosto. Num só dia, houve perto de 1.000 infeções, o valor mais alto dos últimos nove meses.","link":"https://sicnoticias.pt/especiais/coronavirus/2023-09-07-Numero-de-casos-de-covid-19-dispara-pico-atingido-no-final-de-agosto-61027bb7"}]
