[{"time":"2023-10-06 06:48:31","titulo":"Hoje há greve nacional de professores e educadores","thumb":"https://images.impresa.pt/sicnot/2023-04-20-Sala-de-aulas.jpg-a8ea3522-2/1.91x1?wm=true&outputFormat=jpeg","desc":"Cerca de três semanas após o arranque do ano letivo, docentes e educadores voltam a parar para exigir velhas reivindicações, como a contabilização integral do tempo de serviço congelado.","link":"https://sicnoticias.pt/pais/2023-10-06-Professores-e-educadores-em-greve-tres-semanas-apos-o-arranque-do-ano-letivo-7c3fad0c"}]
