[{"time":"2023-10-03 20:25:43","titulo":"Quem são os ativistas da Climáximo que pararam a 2.ª Circular?","thumb":"https://static.globalnoticias.pt/dn/image.jpg?brand=DN&type=generate&guid=1bc7b726-48fe-4cde-bbd6-a3e7c81eb730&w=800&h=420&watermark=true&t=20231003210600","desc":"Onze jovens ativistas que pararam a 2.ª Circular vão quarta-feira a tribunal. Pertencem ao coletivo Climáximo, que quer levar o debate da crise climática diretamente às pessoas.","link":"https://www.dn.pt/edicao-do-dia/04-out-2023/quem-sao-os-ativistas-da-climaximo-que-pararam-a-2-circular-17107414.html"}]
