[{"time":"2023-08-22 23:45:28","titulo":"Filha de idoso morto no hospital de Loures vai com o caso para tribunal","thumb":"https://static.globalnoticias.pt/dn/image.jpg?brand=DN&type=generate&guid=62dc1fb0-a3f8-4c46-8b13-4466b19c274d&w=800&h=420&watermark=true&t=20230823003200","desc":"Ana Pereira não se conforma com a morte do pai, de 93 anos, no corredor do Hospital Beatriz Ângelo, onde esteve cinco horas à espera para ser transferido para Santa Maria. \"Não quero que se volte a repetir com mais ninguém\", disse à SIC.","link":"https://www.dn.pt/sociedade/filha-de-idoso-morto-no-hospital-de-loures-vai-com-o-caso-para-tribunal-16900488.html"}]
