[{"time":"2023-10-26 14:27:19","titulo":"Governo não impõe travão à actualização de rendas e apoia inquilinos directamente","thumb":"https://imagens.publico.pt/imagens.aspx/1853861?tp=UH&db=IMAGENS&type=JPG&share=1&o=BarraFacebook_Publico.png","desc":"Terão direito ao apoio os inquilinos com taxas de esforço superiores a 35% e rendimentos até ao sexto escalão de IRS.","link":"https://www.publico.pt/2023/10/26/economia/noticia/governo-nao-impoe-travao-actualizacao-rendas-apoia-inquilinos-directamente-2068109"}]
