[{"time":"2023-12-24 15:06:18","titulo":"Papa Francisco lembra os que sofrem em todo o mundo","thumb":"https://images.impresa.pt/sicnot/2023-12-24-video.0000000.jpg-0993b638/1.91x1?wm=true&outputFormat=jpeg","desc":"Milhares de pessoas assistiram, esta manhã, na Praça de S. Pedro ao habitual angelus de domingo. Na véspera de Natal, o Papa Francisco lembrou os que sofrem em todo o mundo.","link":"https://sicnoticias.pt/mundo/2023-12-24-Papa-Francisco-lembra-os-que-sofrem-em-todo-o-mundo-fb359bbe"}]
