[{"time":"2023-09-07 20:27:13","titulo":"Coabitação. Marcelo arrefece confronto com Costa","thumb":"https://static.globalnoticias.pt/dn/image.jpg?brand=DN&type=generate&guid=6e92e43d-eaba-472e-8141-195d0fa6155a&w=800&h=420&watermark=true&t=20230907211300","desc":"Presidente qualifica promessas do PM como \"sinais de esperança no futuro\". Nega \"querela institucional\" e diz que nunca pretendeu substituir-se ao Governo, de quem é \"controleiro\".","link":"https://www.dn.pt/politica/coabitacao-marcelo-arrefece-confronto-com-costa-16985843.html"}]
