[{"time":"2023-11-04 22:27:54","titulo":"Ministro propõe aumento de 8,5% na atualização salarial dos médicos","thumb":"https://media-manager.noticiasaominuto.com/1280/41669533.JPG","desc":"O ministro da Saúde propôs hoje aos sindicatos o aumento de 5,5% para 8,5% da atualização salarial dos médicos, uma contraproposta que diz aproximar-se das reivindicações sindicais se se considerar igualmente a redução do horário de trabalho.","link":"https://www.noticiasaominuto.com/pais/2434046/ministro-propoe-aumento-de-8-5-na-atualizacao-salarial-dos-medicos"}]
