[{"time":"2023-12-14 19:06:12","titulo":"Orbán saiu da sala para permitir um acordo: UE abre negociações para a adesão da Ucrânia","thumb":"https://img.iol.pt/preset/6324789c0cf2ea4f0a5caf68/og/cnn","desc":"“A União Europeia está a preparar-se para cometer um erro terrível e temos de o evitar, mesmo que 26 Estados-membros queiram cometer o erro”, afirmou Orbán quarta-feira. Um dia depois, e apesar de manter a sua oposição, certo é que houve um acordo","link":"https://cnnportugal.iol.pt/conselho-europeu/ucrania/conselho-europeu-decide-abrir-negociacoes-de-adesao-com-ucrania/20231214/657b3e10d34e371fc0baf7b8"}]
