[{"time":"2023-09-10 07:26:46","titulo":"Marrocos decreta três dias de luto nacional devido ao sismo","thumb":"https://images.impresa.pt/sicnot/2023-09-10-Sismo-Marrocos.jpg-042c9244-1/1.91x1?wm=true&outputFormat=jpeg","desc":"O sismo que atingiu, esta sexta-feira, o país provocou mais de 2.000 mortos e milhares ficaram feridos. Os líderes de todo o mundo manifestaram solidariedade para com Marrocos e disponibilizaram ajuda.","link":"https://sicnoticias.pt/mundo/2023-09-10-Marrocos-decreta-tres-dias-de-luto-nacional-devido-ao-sismo-3d23938a"}]
