[{"time":"2023-09-03 15:14:47","titulo":"Alerta vermelho na região de Madrid devido a chuvas torrenciais","thumb":"https://images.impresa.pt/sicnot/2023-09-03-chuva-espanha-estrada.JPG-b583c225-2/1.91x1?wm=true&outputFormat=jpeg","desc":"Agência Estatal de Meteorologia espanhola ativou o alerta vermelho na Comunidade de Madrid e em Castela-La Mancha. Sul e oeste da Comunidade de Madrid deverão ser as zonas mais afetadas pelas chuvas torrenciais.","link":"https://sicnoticias.pt/meteorologia/2023-09-03-Alerta-vermelho-na-regiao-de-Madrid-adiado-jogo-entre-Atletico-e-Sevilha-27f716bb"}]
