[{"time":"2023-12-23 11:25:20","titulo":"Luís Montenegro ignora Passos Coelho e André Ventura","thumb":"https://images.impresa.pt/expresso/2023-12-21-foto-Ana-Baiao_T-_IDP.png-51179c0d/1.91x1?wm=true&outputFormat=jpeg","desc":"O líder do PSD tenta contrariar acusação de falta de propostas e vai destrunfando. Coligação pré-eleitoral para as legislativas e europeias com o CDS está fechada","link":"https://expresso.pt/politica/crise/2023-12-23-Luis-Montenegro-ignora-Passos-Coelho-e-Andre-Ventura-11cc387d"}]
