[{"time":"2023-11-12 09:25:12","titulo":"″[Este caso] é um desaire tenebroso para a experiência do poder de António Costa″","thumb":"https://static.globalnoticias.pt/dn/image.jpg?brand=DN&type=generate&guid=f63aeba0-efe1-4d4b-8237-5fde6357ba59&w=800&h=420&watermark=true&t=20231112004800","desc":"Ao DN, o investigador no Instituto de Ciências Sociais de Lisboa (ICS), considera que o PS tem dois bons nomes para a sucessão de António Costa. No entanto, diz, o caso mancha a reputação do primeiro-ministro demissionário e do próprio partido.","link":"https://www.dn.pt/politica/este-caso-e-um-desaire-tenebroso-para-a-experiencia-do-poder-de-antonio-costa-17320922.html"}]
