[{"time":"2023-09-22 20:47:03","titulo":"Eça. Corrida contra o tempo na polémica da trasladação","thumb":"https://static.globalnoticias.pt/dn/image.jpg?brand=DN&type=generate&guid=b643f3dd-0f49-4c31-8269-8aa078b9a58d&w=800&h=420&watermark=true&t=20230922213700","desc":"Supremo Tribunal Administrativo recebeu ontem resposta do Parlamento sobre providência cautelar interposta por familiares que se opõem à trasladação dos restos mortais do escritor para o Panteão.","link":"https://www.dn.pt/cultura/eca-corrida-contra-o-tempo-na-polemica-da-trasladacao-17069857.html"}]
