[{"time":"2023-11-04 22:07:03","titulo":"Hamas diz que ataques israelitas mataram ″mais de 60″ reféns","thumb":"https://static.globalnoticias.pt/dn/image.jpg?brand=DN&type=generate&guid=446a1036-9827-487a-88fe-d2e4226938c6&w=800&h=420&watermark=true&t=20231104211500","desc":"O exército israelita informou que entrou no sul a Faixa de Gaza, mantendo a ofensiva na região contra o Hamas apesar dos apelos para um cessar-fogo humanitário.","link":"https://www.dn.pt/internacional/guterres-horrorizado-com-ataque-israelita-contra-ambulancias-em-gaza-17281411.html"}]
